parsecfi/__init__.py
parsecfi/parsecfi.py
parsecfi/lib/__init__.py
parsecfi/lib/endpoints.py
parsecfi/lib/endpoints_list/__init__.py
parsecfi/lib/endpoints_list/address.py
parsecfi/lib/endpoints_list/candles.py
parsecfi/lib/endpoints_list/conc_liquidity_positions.py
parsecfi/lib/endpoints_list/contract_logs.py
parsecfi/lib/endpoints_list/dex_trades.py
parsecfi/lib/endpoints_list/lending_market.py
parsecfi/lib/endpoints_list/lending_positions.py
parsecfi/lib/endpoints_list/liquidity_pools.py
parsecfi/lib/endpoints_list/nft_collection.py
parsecfi/lib/endpoints_list/nft_trades.py
parsecfi/lib/endpoints_list/token_acc.py
parsecfi/lib/endpoints_list/token_holders.py
parsecfi/lib/endpoints_list/trade_metrics.py
parsecfi/lib/endpoints_list/transactions.py
parsecfi/lib/endpoints_list/transfers.py
parsecfi/lib/endpoints_list/trending_contracts.py
parsecfi-0.1.6.dist-info/METADATA
parsecfi-0.1.6.dist-info/WHEEL
parsecfi-0.1.6.dist-info/top_level.txt
parsecfi-0.1.6.dist-info/RECORD
