Metadata-Version: 2.1
Name: parsecfi
Version: 0.1.6
Summary: Python SDK for the Parsec API
Home-page: UNKNOWN
Author: PARSEC FINANCE INC.
License: MIT
Platform: UNKNOWN
Requires-Dist: requests
Requires-Dist: pandas
